Topsis_102017189/102017189.py
Topsis_102017189/__init__.py
topsis_102017184/102017184.py
topsis_102017184/__init__.py
topsis_102017189_1/102017189.py
topsis_102017189_1/__init__.py
Topsis_102017184-0.1.dist-info/LICENSE.txt
Topsis_102017184-0.1.dist-info/METADATA
Topsis_102017184-0.1.dist-info/WHEEL
Topsis_102017184-0.1.dist-info/top_level.txt
Topsis_102017184-0.1.dist-info/RECORD
