Metadata-Version: 2.1
Name: Topsis-102017184
Version: 0.1
Summary: Topsis Package
Author: Ishita Kaundal
Author-email: ikaundal_be20@thapar.edu
Keywords: python,video,stream,video stream,camera stream,sockets
Classifier: Development Status :: 1 - Planning
Classifier: Intended Audience :: Developers
Classifier: Programming Language :: Python :: 3
Classifier: Operating System :: Unix
Classifier: Operating System :: MacOS :: MacOS X
Classifier: Operating System :: Microsoft :: Windows
License-File: LICENSE.txt
